streamlit_realtime_audio_recorder/__init__.py
streamlit_realtime_audio_recorder/audio_recorder.py
streamlit_realtime_audio_recorder-0.1.1.dist-info/METADATA
streamlit_realtime_audio_recorder-0.1.1.dist-info/WHEEL
streamlit_realtime_audio_recorder-0.1.1.dist-info/licenses/LICENSE
streamlit_realtime_audio_recorder-0.1.1.dist-info/RECORD
