Metadata-Version: 2.4
Name: streamlit-realtime-audio-recorder
Version: 0.1.1
Summary: A Streamlit component that records audio with real-time silence detection
Project-URL: Bug Tracker, https://github.com/soufiiyane/streamlit-realtime-audio-recorder/issues
Author-email: Soufiyane AIT MOULAY <soufiyane.aitmoulay@gmail.com>
License-File: LICENSE
Classifier: License :: OSI Approved :: MIT License
Classifier: Operating System :: OS Independent
Classifier: Programming Language :: Python :: 3
Requires-Python: >=3.7
Requires-Dist: streamlit>=1.0.1
